Metadata-Version: 1.2
Name: pynetstim
Version: 0.2a0
Summary: brain network stimulation
Home-page: https://github.com/EhsanTadayon/pynetstim
Author: Ehsan Tadayon
Author-email: sunny.tadayon@gmail.com
Maintainer: Ehsan Tadyaon
Maintainer-email: sunny.tadayon@gmail.com
License: MIT
Download-URL: https://github.com/EhsanTadayon/pynetstim/archive/v_0.2-alpha.tar.gz
Keywords: brain network,stimulation,imaging,fMRI,diffusion,TMS
Platform: UNKNOWN
Classifier: Development Status :: 3 - Alpha
Classifier: Intended Audience :: Science/Research
Classifier: Intended Audience :: Developers
Classifier: Topic :: Scientific/Engineering
Classifier: Operating System :: MacOS
Classifier: Operating System :: Unix
Classifier: Topic :: Software Development :: Build Tools
Classifier: License :: OSI Approved :: MIT License
Classifier: Programming Language :: Python :: 3
Classifier: Programming Language :: Python :: 3.6
Classifier: Programming Language :: Python :: 3.7
